{
    "last_updated": "2026-07-14 00:01:37",
    "last_run_date": "2026-07-14",
    "market_type": "overseas",
    "reason": "루멘텀 홀딩스(LITE):SKIP(buy_amount(USD 500.00) < 현재가(USD 799.96) -> 1주도 매수 불가. buy_amount 상향 조정 필요)",
    "exchange_rate": 1507.1,
    "portfolio": {
        "total_value": 19011.7853,
        "cash_balance": 5497.06,
        "holdings": [
            {
                "ticker": "AAPL",
                "alias": "애플",
                "qty": 1,
                "price": 318.97,
                "value": 318.97
            },
            {
                "ticker": "ARKK",
                "alias": "ARK INNOVATION",
                "qty": 6,
                "price": 79.46,
                "value": 476.76
            },
            {
                "ticker": "AVGO",
                "alias": "브로드컴",
                "qty": 3,
                "price": 392.2001,
                "value": 1176.6003
            },
            {
                "ticker": "CCJ",
                "alias": "카메코",
                "qty": 10,
                "price": 92.84,
                "value": 928.4000000000001
            },
            {
                "ticker": "DELL",
                "alias": "델 테크놀로지스",
                "qty": 3,
                "price": 433.55,
                "value": 1300.65
            },
            {
                "ticker": "GLW",
                "alias": "코닝",
                "qty": 17,
                "price": 188.74,
                "value": 3208.58
            },
            {
                "ticker": "GOOGL",
                "alias": "알파벳 A",
                "qty": 3,
                "price": 355.73,
                "value": 1067.19
            },
            {
                "ticker": "ICLN",
                "alias": "ISHARES GLOBAL CLEAN ENERGY",
                "qty": 70,
                "price": 18.891,
                "value": 1322.37
            },
            {
                "ticker": "LITE",
                "alias": "루멘텀 홀딩스",
                "qty": 1,
                "price": 799.96,
                "value": 799.96
            },
            {
                "ticker": "PEP",
                "alias": "펩시코",
                "qty": 6,
                "price": 139.04,
                "value": 834.24
            },
            {
                "ticker": "SCHD",
                "alias": "SCHWAB US DIVIDEND EQUITY",
                "qty": 15,
                "price": 32.555,
                "value": 488.325
            },
            {
                "ticker": "TSLA",
                "alias": "테슬라",
                "qty": 4,
                "price": 398.17,
                "value": 1592.68
            }
        ]
    },
    "positions": {
        "AAPL": {
            "total_qty": 1,
            "lot_count": 1,
            "total_invested": 291.9,
            "current_value": 318.97,
            "lots": [
                {
                    "lot_id": "lot_20260508_170952_AAPL_001",
                    "buy_price": 291.9,
                    "quantity": 1,
                    "buy_date": "2026-05-08",
                    "level": 1,
                    "current_price": 318.97,
                    "pct_change": 9.27
                }
            ],
            "current_price": 318.97,
            "alias": "애플",
            "avg_buy_price": 291.9,
            "unrealized_pnl": 27.07,
            "unrealized_pnl_pct": 9.27,
            "realized_pnl": 0.0,
            "total_pnl": 27.07
        },
        "PEP": {
            "total_qty": 6,
            "lot_count": 2,
            "total_invested": 877.14,
            "current_value": 834.24,
            "lots": [
                {
                    "lot_id": "lot_20260512_003512_PEP_001",
                    "buy_price": 150.05,
                    "quantity": 3,
                    "buy_date": "2026-05-12",
                    "level": 1,
                    "current_price": 139.04,
                    "pct_change": -7.34
                },
                {
                    "lot_id": "lot_20260605_023704_PEP_002",
                    "buy_price": 142.33,
                    "quantity": 3,
                    "buy_date": "2026-06-05",
                    "level": 2,
                    "current_price": 139.04,
                    "pct_change": -2.31
                }
            ],
            "current_price": 139.04,
            "alias": "펩시코",
            "avg_buy_price": 146.19,
            "unrealized_pnl": -42.9,
            "unrealized_pnl_pct": -4.89,
            "realized_pnl": 0.0,
            "total_pnl": -42.9
        },
        "ARKK": {
            "total_qty": 6,
            "lot_count": 1,
            "total_invested": 479.52,
            "current_value": 476.76,
            "lots": [
                {
                    "lot_id": "lot_20260512_003536_ARKK_001",
                    "buy_price": 79.92,
                    "quantity": 6,
                    "buy_date": "2026-05-12",
                    "level": 1,
                    "current_price": 79.46,
                    "pct_change": -0.58
                }
            ],
            "current_price": 79.46,
            "alias": "ARK INNOVATION",
            "avg_buy_price": 79.92,
            "unrealized_pnl": -2.76,
            "unrealized_pnl_pct": -0.58,
            "realized_pnl": 23.22,
            "total_pnl": 20.46
        },
        "SCHD": {
            "total_qty": 15,
            "lot_count": 1,
            "total_invested": 476.1,
            "current_value": 488.32,
            "lots": [
                {
                    "lot_id": "lot_20260512_003547_SCHD_001",
                    "buy_price": 31.74,
                    "quantity": 15,
                    "buy_date": "2026-05-12",
                    "level": 1,
                    "current_price": 32.555,
                    "pct_change": 2.57
                }
            ],
            "current_price": 32.555,
            "alias": "SCHWAB US DIVIDEND EQUITY",
            "avg_buy_price": 31.74,
            "unrealized_pnl": 12.23,
            "unrealized_pnl_pct": 2.57,
            "realized_pnl": 0.0,
            "total_pnl": 12.23
        },
        "ICLN": {
            "total_qty": 70,
            "lot_count": 3,
            "total_invested": 1457.75,
            "current_value": 1322.37,
            "lots": [
                {
                    "lot_id": "lot_20260512_003559_ICLN_001",
                    "buy_price": 22.01,
                    "quantity": 22,
                    "buy_date": "2026-05-12",
                    "level": 1,
                    "current_price": 18.891,
                    "pct_change": -14.17
                },
                {
                    "lot_id": "lot_20260618_000135_ICLN_002",
                    "buy_price": 20.86,
                    "quantity": 23,
                    "buy_date": "2026-06-18",
                    "level": 2,
                    "current_price": 18.891,
                    "pct_change": -9.44
                },
                {
                    "lot_id": "lot_20260627_020129_ICLN_003",
                    "buy_price": 19.75,
                    "quantity": 25,
                    "buy_date": "2026-06-27",
                    "level": 3,
                    "current_price": 18.891,
                    "pct_change": -4.35
                }
            ],
            "current_price": 18.891,
            "alias": "ISHARES GLOBAL CLEAN ENERGY",
            "avg_buy_price": 20.825,
            "unrealized_pnl": -135.38,
            "unrealized_pnl_pct": -9.29,
            "realized_pnl": 0.0,
            "total_pnl": -135.38
        },
        "GOOGL": {
            "total_qty": 3,
            "lot_count": 3,
            "total_invested": 1108.64,
            "current_value": 1067.19,
            "lots": [
                {
                    "lot_id": "lot_20260512_003610_GOOGL_001",
                    "buy_price": 393.85,
                    "quantity": 1,
                    "buy_date": "2026-05-12",
                    "level": 1,
                    "current_price": 355.73,
                    "pct_change": -9.68
                },
                {
                    "lot_id": "lot_20260606_020600_GOOGL_002",
                    "buy_price": 369.66,
                    "quantity": 1,
                    "buy_date": "2026-06-06",
                    "level": 2,
                    "current_price": 355.73,
                    "pct_change": -3.77
                },
                {
                    "lot_id": "lot_20260623_000124_GOOGL_003",
                    "buy_price": 345.13,
                    "quantity": 1,
                    "buy_date": "2026-06-23",
                    "level": 3,
                    "current_price": 355.73,
                    "pct_change": 3.07
                }
            ],
            "current_price": 355.73,
            "alias": "알파벳 A",
            "avg_buy_price": 369.5467,
            "unrealized_pnl": -41.45,
            "unrealized_pnl_pct": -3.74,
            "realized_pnl": 0.0,
            "total_pnl": -41.45
        },
        "TSLA": {
            "total_qty": 4,
            "lot_count": 4,
            "total_invested": 1672.83,
            "current_value": 1592.68,
            "lots": [
                {
                    "lot_id": "lot_20260512_003633_TSLA_001",
                    "buy_price": 438.44,
                    "quantity": 1,
                    "buy_date": "2026-05-12",
                    "level": 1,
                    "current_price": 398.17,
                    "pct_change": -9.18
                },
                {
                    "lot_id": "lot_20260512_143909_TSLA_002",
                    "buy_price": 435.49,
                    "quantity": 1,
                    "buy_date": "2026-05-12",
                    "level": 2,
                    "current_price": 398.17,
                    "pct_change": -8.57
                },
                {
                    "lot_id": "lot_20260519_022217_TSLA_003",
                    "buy_price": 409.9,
                    "quantity": 1,
                    "buy_date": "2026-05-19",
                    "level": 3,
                    "current_price": 398.17,
                    "pct_change": -2.86
                },
                {
                    "lot_id": "lot_20260619_000124_TSLA_004",
                    "buy_price": 389.0,
                    "quantity": 1,
                    "buy_date": "2026-06-19",
                    "level": 4,
                    "current_price": 398.17,
                    "pct_change": 2.36
                }
            ],
            "current_price": 398.17,
            "alias": "테슬라",
            "avg_buy_price": 418.2075,
            "unrealized_pnl": -80.15,
            "unrealized_pnl_pct": -4.79,
            "realized_pnl": 0.0,
            "total_pnl": -80.15
        },
        "AVGO": {
            "total_qty": 3,
            "lot_count": 2,
            "total_invested": 1128.4,
            "current_value": 1176.6,
            "lots": [
                {
                    "lot_id": "lot_20260617_000129_AVGO_001",
                    "buy_price": 382.6,
                    "quantity": 2,
                    "buy_date": "2026-06-17",
                    "level": 1,
                    "current_price": 392.2001,
                    "pct_change": 2.51
                },
                {
                    "lot_id": "lot_20260708_000141_AVGO_002",
                    "buy_price": 363.2,
                    "quantity": 1,
                    "buy_date": "2026-07-08",
                    "level": 2,
                    "current_price": 392.2001,
                    "pct_change": 7.98
                }
            ],
            "current_price": 392.2001,
            "alias": "브로드컴",
            "avg_buy_price": 376.1333,
            "unrealized_pnl": 48.2,
            "unrealized_pnl_pct": 4.27,
            "realized_pnl": -35.72,
            "total_pnl": 12.48
        },
        "LITE": {
            "total_qty": 1,
            "lot_count": 1,
            "total_invested": 875.53,
            "current_value": 799.96,
            "lots": [
                {
                    "lot_id": "lot_20260617_000138_LITE_001",
                    "buy_price": 875.53,
                    "quantity": 1,
                    "buy_date": "2026-06-17",
                    "level": 1,
                    "current_price": 799.96,
                    "pct_change": -8.63
                }
            ],
            "current_price": 799.96,
            "alias": "루멘텀 홀딩스",
            "avg_buy_price": 875.53,
            "unrealized_pnl": -75.57,
            "unrealized_pnl_pct": -8.63,
            "realized_pnl": 67.05,
            "total_pnl": -8.52
        },
        "DELL": {
            "total_qty": 3,
            "lot_count": 2,
            "total_invested": 1264.34,
            "current_value": 1300.65,
            "lots": [
                {
                    "lot_id": "lot_20260619_020113_DELL_001",
                    "buy_price": 427.22,
                    "quantity": 2,
                    "buy_date": "2026-06-19",
                    "level": 1,
                    "current_price": 433.55,
                    "pct_change": 1.48
                },
                {
                    "lot_id": "lot_20260622_212221_DELL_002",
                    "buy_price": 409.9,
                    "quantity": 1,
                    "buy_date": "2026-06-22",
                    "level": 2,
                    "current_price": 433.55,
                    "pct_change": 5.77
                }
            ],
            "current_price": 433.55,
            "alias": "델 테크놀로지스",
            "avg_buy_price": 421.4467,
            "unrealized_pnl": 36.31,
            "unrealized_pnl_pct": 2.87,
            "realized_pnl": 0.0,
            "total_pnl": 36.31
        },
        "GLW": {
            "total_qty": 17,
            "lot_count": 3,
            "total_invested": 3333.52,
            "current_value": 3208.58,
            "lots": [
                {
                    "lot_id": "lot_20260707_000139_GLW_001",
                    "buy_price": 200.18,
                    "quantity": 5,
                    "buy_date": "2026-07-07",
                    "level": 1,
                    "current_price": 188.74,
                    "pct_change": -5.71
                },
                {
                    "lot_id": "lot_20260708_000201_GLW_002",
                    "buy_price": 183.31,
                    "quantity": 2,
                    "buy_date": "2026-07-08",
                    "level": 2,
                    "current_price": 188.74,
                    "pct_change": 2.96
                },
                {
                    "lot_id": "lot_20260709_232341_GLW_003",
                    "buy_price": 196.6,
                    "quantity": 10,
                    "buy_date": "2026-07-09",
                    "level": 3,
                    "current_price": 188.74,
                    "pct_change": -4.0
                }
            ],
            "current_price": 188.74,
            "alias": "코닝",
            "avg_buy_price": 196.0894,
            "unrealized_pnl": -124.94,
            "unrealized_pnl_pct": -3.75,
            "realized_pnl": 75.12,
            "total_pnl": -49.82
        },
        "CCJ": {
            "total_qty": 10,
            "lot_count": 1,
            "total_invested": 940.6,
            "current_value": 928.4,
            "lots": [
                {
                    "lot_id": "lot_20260708_000149_CCJ_001",
                    "buy_price": 94.06,
                    "quantity": 10,
                    "buy_date": "2026-07-08",
                    "level": 1,
                    "current_price": 92.84,
                    "pct_change": -1.3
                }
            ],
            "current_price": 92.84,
            "alias": "카메코",
            "avg_buy_price": 94.06,
            "unrealized_pnl": -12.2,
            "unrealized_pnl_pct": -1.3,
            "realized_pnl": 0.0,
            "total_pnl": -12.2
        }
    },
    "realized_pnl_by_ticker": {
        "GLW": 75.12,
        "IBM": -30.42,
        "LITE": 67.05,
        "RGTI": -266.31,
        "AVGO": -35.72,
        "ARM": -364.57,
        "O": 10.24,
        "PG": 19.05,
        "DUK": 11.4,
        "ARKK": 23.22
    },
    "regime_state_by_ticker": {},
    "enabled_tickers": ["AAPL", "PEP", "ARKK", "SCHD", "ICLN", "GOOGL", "AVGO", "TSLA", "LITE", "DELL", "CCJ"],
    "risk_summary": {
        "next_level_needs": 5500.0,
        "max_potential_exposure": 555500.0,
        "stale_info": [
            {
                "ticker": "AAPL",
                "alias": "애플",
                "last_trade_date": "2026-05-08",
                "days_stale": 67
            },
            {
                "ticker": "SCHD",
                "alias": "SCHWAB US DIVIDEND EQUITY",
                "last_trade_date": "2026-05-12",
                "days_stale": 63
            },
            {
                "ticker": "PEP",
                "alias": "펩시코",
                "last_trade_date": "2026-06-05",
                "days_stale": 39
            },
            {
                "ticker": "LITE",
                "alias": "루멘텀 홀딩스",
                "last_trade_date": "2026-06-17",
                "days_stale": 27
            },
            {
                "ticker": "TSLA",
                "alias": "테슬라",
                "last_trade_date": "2026-06-19",
                "days_stale": 25
            },
            {
                "ticker": "DELL",
                "alias": "델 테크놀로지스",
                "last_trade_date": "2026-06-22",
                "days_stale": 22
            },
            {
                "ticker": "GOOGL",
                "alias": "알파벳 A",
                "last_trade_date": "2026-06-23",
                "days_stale": 21
            },
            {
                "ticker": "ICLN",
                "alias": "ISHARES GLOBAL CLEAN ENERGY",
                "last_trade_date": "2026-06-27",
                "days_stale": 17
            },
            {
                "ticker": "AVGO",
                "alias": "브로드컴",
                "last_trade_date": "2026-07-08",
                "days_stale": 6
            },
            {
                "ticker": "CCJ",
                "alias": "카메코",
                "last_trade_date": "2026-07-08",
                "days_stale": 6
            },
            {
                "ticker": "ARKK",
                "alias": "ARK INNOVATION",
                "last_trade_date": "2026-07-09",
                "days_stale": 5
            },
            {
                "ticker": "GLW",
                "alias": "코닝",
                "last_trade_date": "2026-07-09",
                "days_stale": 5
            }
        ],
        "risk_score": 84,
        "deductions": [
            {
                "reason": "단일 종목 집중도 과다",
                "points": 3.8
            },
            {
                "reason": "장기 정체 종목",
                "points": 12
            }
        ],
        "sync_error": false,
        "alerts": ["⚠️ 장기 정체 종목 존재 (3개)"],
        "max_ticker_concentration": 16.88,
        "high_level_ratio": 0.0
    }
}